src/__init__.py
src/main.py
clipmate-0.1.1.dist-info/LICENSE
clipmate-0.1.1.dist-info/METADATA
clipmate-0.1.1.dist-info/WHEEL
clipmate-0.1.1.dist-info/entry_points.txt
clipmate-0.1.1.dist-info/top_level.txt
clipmate-0.1.1.dist-info/RECORD
