Metadata-Version: 2.1
Name: clipmate
Version: 0.1.1
Summary: A Python tool for sharing and managing clipboard content over a private local network
Home-page: https://github.com/MuhammadRamzy/Cross-platform-clipboard
Author: Muhammad Ramzy
Author-email: mhdramzy777@gmail.com
Classifier: Programming Language :: Python :: 3
Classifier: License :: OSI Approved :: MIT License
Classifier: Operating System :: OS Independent
Requires-Python: >=3.6
License-File: LICENSE
Requires-Dist: pyperclip
Requires-Dist: termcolor
Requires-Dist: pyfiglet
